yarn_api_client/__init__.py
yarn_api_client/__main__.py
yarn_api_client/application_master.py
yarn_api_client/auth.py
yarn_api_client/base.py
yarn_api_client/constants.py
yarn_api_client/errors.py
yarn_api_client/hadoop_conf.py
yarn_api_client/history_server.py
yarn_api_client/main.py
yarn_api_client/node_manager.py
yarn_api_client/resource_manager.py
yarn_api_client-1.0.3.dist-info/LICENSE
yarn_api_client-1.0.3.dist-info/METADATA
yarn_api_client-1.0.3.dist-info/WHEEL
yarn_api_client-1.0.3.dist-info/entry_points.txt
yarn_api_client-1.0.3.dist-info/top_level.txt
yarn_api_client-1.0.3.dist-info/RECORD
