Metadata-Version: 2.1
Name: yarn-api-client
Version: 1.0.3
Summary: Python client for Hadoop® YARN API
Home-page: https://github.com/CODAIT/hadoop-yarn-api-python-client
Author: Iskandarov Eduard
Author-email: eduard.iskandarov@ya.ru
Maintainer: Dmitry Romanenko
Maintainer-email: dmitry@romanenko.in
License: BSD
Platform: UNKNOWN
Classifier: Intended Audience :: Developers
Classifier: License :: OSI Approved :: BSD License
Classifier: Operating System :: OS Independent
Classifier: Programming Language :: Python :: 3.6
Classifier: Programming Language :: Python :: 3.7
Classifier: Programming Language :: Python :: 3.8
Classifier: Programming Language :: Python :: 3.9
Classifier: Programming Language :: Python :: 3.10
Classifier: Topic :: System :: Distributed Computing
License-File: LICENSE
Requires-Dist: requests (<3.0,>=2.7)
